slack_message_pipe/__init__.py
slack_message_pipe/channel_history_export.py
slack_message_pipe/cli.py
slack_message_pipe/helpers.py
slack_message_pipe/intermediate_data.py
slack_message_pipe/locales.py
slack_message_pipe/settings.py
slack_message_pipe/slack_message_pipe.ini
slack_message_pipe/slack_service.py
slack_message_pipe/slack_text_converter.py
slack_message_pipe/fonts/LICENSE
slack_message_pipe/fonts/NotoSans-Bold.ttf
slack_message_pipe/fonts/NotoSans-BoldItalic.ttf
slack_message_pipe/fonts/NotoSans-Italic.ttf
slack_message_pipe/fonts/NotoSans-Regular.ttf
slack_message_pipe/fonts/NotoSansMono-Bold.ttf
slack_message_pipe/fonts/NotoSansMono-Regular.ttf
slack_message_pipe-2.0.0.dist-info/entry_points.txt
slack_message_pipe-2.0.0.dist-info/LICENSE
slack_message_pipe-2.0.0.dist-info/WHEEL
slack_message_pipe-2.0.0.dist-info/METADATA
slack_message_pipe-2.0.0.dist-info/RECORD
