Metadata-Version: 2.1
Name: slack_message_pipe
Version: 2.0.0
Summary: Command line tool for exporting the text contents of any Slack channel to a PDF file.
Author-email: Dean Thompson <deansherthompson@gmail.com>
Requires-Python: >=3.10
Classifier: Environment :: Console
Classifier: Intended Audience :: End Users/Desktop
Classifier: License :: OSI Approved :: MIT License
Classifier: Operating System :: OS Independent
Classifier: Programming Language :: Python
Classifier: Programming Language :: Python :: 3.11
Requires-Dist: Babel>=2.9.1,<3.0.0
Requires-Dist: python-dateutil>=2.8.0,<3.0.0
Requires-Dist: slack_sdk>=3.15.2,<4.0.0
Requires-Dist: tzlocal>=5.2,<6.0
Requires-Dist: tox>=3.24.4 ; extra == "dev"
Requires-Dist: flake8>=4.0.0 ; extra == "dev"
Requires-Dist: black>=22.0.0 ; extra == "dev"
Requires-Dist: isort>=5.0.0 ; extra == "dev"
Requires-Dist: pylint>=2.0.0 ; extra == "dev"
Requires-Dist: mypy>=1.8.0 ; extra == "dev"
Requires-Dist: pre-commit>=2.0.0 ; extra == "dev"
Requires-Dist: cfgv>=3.3.1 ; extra == "dev"
Requires-Dist: types-tzlocal ; extra == "dev"
Requires-Dist: types-python-dateutil ; extra == "dev"
Requires-Dist: pytest>=7.0.0 ; extra == "test"
Requires-Dist: pytest-cov>=3.0.0 ; extra == "test"
Requires-Dist: coverage[toml]>=5.5 ; extra == "test"
Requires-Dist: PyPDF2>=1.26.0 ; extra == "test"
Project-URL: Homepage, https://github.com/deansher/slack-message-pipe
Provides-Extra: dev
Provides-Extra: test
